orthrus/__init__.py
orthrus/core/__init__.py
orthrus/core/dataset.py
orthrus/core/helper.py
orthrus/core/pipeline.py
orthrus/core/scratch.py
orthrus/decomposition/__init__.py
orthrus/decomposition/general.py
orthrus/manifold/__init__.py
orthrus/manifold/mds.py
orthrus/model_selection/__init__.py
orthrus/model_selection/partitioning.py
orthrus/preprocessing/__init__.py
orthrus/preprocessing/batch_corrections.py
orthrus/preprocessing/imputation.py
orthrus/preprocessing/normalizations.py
orthrus/solvers/__init__.py
orthrus/solvers/linear.py
orthrus/solvers/nonlinear.py
orthrus/sparse/__init__.py
orthrus/sparse/classifiers/__init__.py
orthrus/sparse/classifiers/svm.py
orthrus/sparse/feature_selection/IterativeFeatureRemoval.py
orthrus/sparse/feature_selection/IterativeFeatureRemoval2.py
orthrus/sparse/feature_selection/__init__.py
orthrus/sparse/feature_selection/helper.py
orthrus/sparse/feature_selection/kffs.py
orthrus/sparse/feature_selection/kfold_loso_ifr.py
orthrus/sparse/feature_selection/kfold_shuffle_ifr.py
orthrus/sparse/feature_selection/pathway_selection.py
orthrus/sparse/feature_selection/pca_snr_selection.py
orthrus/sparse/feature_selection/sabs.py
orthrus-1.0.9.dist-info/LICENSE
orthrus-1.0.9.dist-info/METADATA
orthrus-1.0.9.dist-info/WHEEL
orthrus-1.0.9.dist-info/top_level.txt
orthrus-1.0.9.dist-info/RECORD
