Metadata-Version: 2.1
Name: orthrus
Version: 1.0.9
Summary: A python package for scaling and automating pre-processing, visualization, classification, and features selection of generic data sets.
Home-page: https://github.com/ekehoe32/orthrus
Author: Eric Kehoe, Kartikay Sharma
Author-email: ekehoe32@gmail.com
License: UNKNOWN
Download-URL: https://github.com/ekehoe32/orthrus/archive/refs/tags/v1.0.9.tar.gz
Platform: UNKNOWN
Classifier: Programming Language :: Python :: 3
Classifier: License :: OSI Approved :: GNU General Public License v3 (GPLv3)
Classifier: Operating System :: OS Independent
Requires-Python: >=3.7
License-File: LICENSE
